i3_workspace_groups-0.4.7.data/scripts/i3-assign-workspace-to-group
i3_workspace_groups-0.4.7.data/scripts/i3-focus-on-workspace
i3_workspace_groups-0.4.7.data/scripts/i3-groups-polybar-module
i3_workspace_groups-0.4.7.data/scripts/i3-move-to-workspace
i3_workspace_groups-0.4.7.data/scripts/i3-rename-workspace
i3_workspace_groups-0.4.7.data/scripts/i3-select-workspace-group
i3_workspace_groups-0.4.7.data/scripts/i3-switch-active-workspace-group
i3_workspace_groups-0.4.7.data/scripts/i3-workspace-groups-client
i3wsgroups/__init__.py
i3wsgroups/__version__.py
i3wsgroups/autoname_workspaces.py
i3wsgroups/cli.py
i3wsgroups/cli_util.py
i3wsgroups/config.py
i3wsgroups/controller.py
i3wsgroups/default_config.toml
i3wsgroups/i3_proxy.py
i3wsgroups/icons.py
i3wsgroups/log_util.py
i3wsgroups/polybar_module_updater.py
i3wsgroups/py_client.py
i3wsgroups/workspace_names.py
i3_workspace_groups-0.4.7.dist-info/LICENSE
i3_workspace_groups-0.4.7.dist-info/METADATA
i3_workspace_groups-0.4.7.dist-info/WHEEL
i3_workspace_groups-0.4.7.dist-info/entry_points.txt
i3_workspace_groups-0.4.7.dist-info/top_level.txt
i3_workspace_groups-0.4.7.dist-info/RECORD
