Metadata-Version: 2.1
Name: i3-workspace-groups
Version: 0.4.7
License: MIT License
Classifier: Development Status :: 3 - Alpha
Classifier: Intended Audience :: Developers
Classifier: Operating System :: POSIX :: Linux
Classifier: License :: OSI Approved :: MIT License
Classifier: Programming Language :: Python :: 3.8
Classifier: Programming Language :: Python :: 3.9
Classifier: Programming Language :: Python :: 3.10
Classifier: Programming Language :: Python :: 3.11
Classifier: Programming Language :: Python :: 3.12
Requires-Python: >=3.9
License-File: LICENSE
Requires-Dist: i3ipc ~=2.2
Requires-Dist: toml ~=0.10
Requires-Dist: typing-extensions
Requires-Dist: exceptiongroup
Provides-Extra: dev
Requires-Dist: pip-tools ~=7.3 ; extra == 'dev'
Requires-Dist: pylint ~=3.0 ; extra == 'dev'
Requires-Dist: ruff ; extra == 'dev'
Requires-Dist: pyright ; extra == 'dev'
Requires-Dist: yapf ~=0.32 ; extra == 'dev'
Requires-Dist: isort ~=5.10 ; extra == 'dev'
Requires-Dist: tox ~=3.25 ; extra == 'dev'
Requires-Dist: pytest ~=7.3 ; extra == 'dev'
Requires-Dist: pytest-cov ; extra == 'dev'
Requires-Dist: validate-pyproject ; extra == 'dev'
Requires-Dist: setuptools-scm ; extra == 'dev'
Provides-Extra: dev_extra
Requires-Dist: ipython ~=8.14 ; extra == 'dev_extra'
Requires-Dist: jupytext ~=1.0 ; extra == 'dev_extra'
Requires-Dist: rich[jupyter] ; extra == 'dev_extra'
Requires-Dist: pyflyby ~=1.7 ; extra == 'dev_extra'
Requires-Dist: jupyterlab ~=4.0 ; extra == 'dev_extra'
Requires-Dist: ipykernel ~=6.13 ; extra == 'dev_extra'
Requires-Dist: ipywidgets ~=7.7 ; extra == 'dev_extra'
